BlockPayments/BlockPayments.py
BlockPayments/__init__.py
BlockPayments-0.0.1.dist-info/LICENSE
BlockPayments-0.0.1.dist-info/METADATA
BlockPayments-0.0.1.dist-info/WHEEL
BlockPayments-0.0.1.dist-info/top_level.txt
BlockPayments-0.0.1.dist-info/RECORD
