Metadata-Version: 2.1
Name: BlockPayments
Version: 0.0.1
Summary: A Python wrapper for the BlockPayments API.
Home-page: https://github.com/HexyeDev/BlockPayments.py
Author: Hexye
License: MIT
Keywords: blockpayments,blockpayments api,blockpayments python,blockpayments wrapper,blockpayments.py
Classifier: Development Status :: 5 - Production/Stable
Classifier: Intended Audience :: Developers
Classifier: License :: OSI Approved :: MIT License
Classifier: Programming Language :: Python :: 3.9
License-File: LICENSE
Requires-Dist: requests
Requires-Dist: aiohttp
